dsw/config/__init__.py
dsw/config/build_info.py
dsw/config/keys.py
dsw/config/logging.py
dsw/config/model.py
dsw/config/parser.py
dsw/config/sentry.py
dsw_config-4.26.1.dist-info/licenses/LICENSE
dsw_config-4.26.1.dist-info/METADATA
dsw_config-4.26.1.dist-info/WHEEL
dsw_config-4.26.1.dist-info/top_level.txt
dsw_config-4.26.1.dist-info/RECORD
