Metadata-Version: 2.4
Name: dsw-config
Version: 4.26.1
Summary: Library for DSW config manipulation
Author-email: Marek Suchánek <marek.suchanek@ds-wizard.org>
License: Apache License 2.0
Project-URL: Homepage, https://ds-wizard.org
Project-URL: Repository, https://github.com/ds-wizard/engine-tools
Project-URL: Documentation, https://guide.ds-wizard.org
Keywords: dsw,config,yaml,parser
Classifier: Development Status :: 5 - Production/Stable
Classifier: License :: OSI Approved :: Apache Software License
Classifier: Programming Language :: Python
Classifier: Programming Language :: Python :: 3.12
Classifier: Programming Language :: Python :: 3.13
Classifier: Topic :: Text Processing
Classifier: Topic :: Utilities
Requires-Python: <4,>=3.12
License-File: LICENSE
Requires-Dist: PyYAML
Requires-Dist: sentry-sdk
Dynamic: license-file
